masked_norm/__init__.py
masked_norm/functional.py
masked_norm/nn.py
masked_norm/util.py
masked_norm/validation.py
masked_norm-2025.12.dist-info/licenses/LICENSE
masked_norm-2025.12.dist-info/METADATA
masked_norm-2025.12.dist-info/WHEEL
masked_norm-2025.12.dist-info/top_level.txt
masked_norm-2025.12.dist-info/RECORD
