Metadata-Version: 2.4
Name: masked_norm
Version: 2025.12
Summary: A modern implementation of normalization layers
Author: algmarques
Maintainer: algmarques
License-Expression: MIT
Project-URL: Repository, https://github.com/algmarques/masked_norm.git
Requires-Python: >=3.12.9
License-File: LICENSE
Requires-Dist: torch>=2.7.1
Requires-Dist: numpy>=2.3.1
Dynamic: license-file
